cursor_boilerplate/__init__.py
cursor_boilerplate/cli.py
cursor_boilerplate/.cursor/rules/always.mdc
cursor_boilerplate/.cursor/rules/fastapi.mdc
cursor_boilerplate/.cursor/rules/task.mdc
cursor_boilerplate/.cursor/rules/vercel_nextjs.mdc
cursor_boilerplate-0.7.7.dist-info/METADATA
cursor_boilerplate-0.7.7.dist-info/WHEEL
cursor_boilerplate-0.7.7.dist-info/entry_points.txt
cursor_boilerplate-0.7.7.dist-info/top_level.txt
cursor_boilerplate-0.7.7.dist-info/RECORD
