Metadata-Version: 2.4
Name: cursor-boilerplate
Version: 0.7.7
Summary: A boilerplate project for Cursor IDE
Author-email: Your Name <your.email@example.com>
License: MIT
Project-URL: Homepage, https://github.com/yourusername/cursor-boilerplate
Classifier: Programming Language :: Python :: 3
Classifier: Operating System :: OS Independent
Requires-Python: >=3.6
Requires-Dist: click
Requires-Dist: build
Requires-Dist: twine
